src/__init__.py
src/ReAct/agents.py
src/ReAct/llm.py
src/ReAct/prompt.py
src/ReAct/str.py
src/ReAct/test.py
src/ReAct/tool.py
src/assistants/__init__.py
src/assistants/assistants.py
src/persona_bots/__init__.py
src/persona_bots/conversational_assistants.py
vuhosi_atlas-0.1.1.dist-info/METADATA
vuhosi_atlas-0.1.1.dist-info/WHEEL
vuhosi_atlas-0.1.1.dist-info/licenses/LICENSE
vuhosi_atlas-0.1.1.dist-info/RECORD
