Metadata-Version: 2.3
Name: vuhosi-atlas
Version: 0.1.1
Summary: Atlas - Yet Another (AI) Agentic Framework
Project-URL: Homepage, https://github.com/Vuhosi/Atlas
Project-URL: Repository, https://github.com/Vuhosi/Atlas
Author-email: theyashwanthsai <taddishetty34@gmail.com>
License-File: LICENSE
Classifier: License :: OSI Approved :: MIT License
Classifier: Operating System :: OS Independent
Classifier: Programming Language :: Python :: 3
